byte_live_room_biubiu/Widget.py
byte_live_room_biubiu/__init__.py
byte_live_room_biubiu/__main__.py
byte_live_room_biubiu/byteClickLiveRoomFunction.py
byte_live_room_biubiu/formUi.py
byte_live_room_biubiu/starp.py
byte_live_room_biubiu-0.0.9.dist-info/LICENSE
byte_live_room_biubiu-0.0.9.dist-info/METADATA
byte_live_room_biubiu-0.0.9.dist-info/WHEEL
byte_live_room_biubiu-0.0.9.dist-info/top_level.txt
byte_live_room_biubiu-0.0.9.dist-info/RECORD
